run_cpp.py
cpp_executor-0.1.0.dist-info/licenses/LICENSE
cpp_executor-0.1.0.dist-info/METADATA
cpp_executor-0.1.0.dist-info/WHEEL
cpp_executor-0.1.0.dist-info/top_level.txt
cpp_executor-0.1.0.dist-info/RECORD
