Metadata-Version: 2.4
Name: cpp_executor
Version: 0.1.0
Summary: Run C++ code from Python easily
Author-email: Your Name <you@example.com>
License: MIT
Classifier: Programming Language :: Python :: 3
Classifier: License :: OSI Approved :: MIT License
Classifier: Operating System :: OS Independent
Requires-Python: >=3.8
License-File: LICENSE
Dynamic: license-file
